{
	"cmake" : 
	{
		"generator" : 
		{
			"multiConfig" : false,
			"name" : "Ninja"
		},
		"paths" : 
		{
			"cmake" : "C:/Users/Silence/AppData/Local/JetBrains/Toolbox/apps/CLion/ch-0/213.6461.75/bin/cmake/win/bin/cmake.exe",
			"cpack" : "C:/Users/Silence/AppData/Local/JetBrains/Toolbox/apps/CLion/ch-0/213.6461.75/bin/cmake/win/bin/cpack.exe",
			"ctest" : "C:/Users/Silence/AppData/Local/JetBrains/Toolbox/apps/CLion/ch-0/213.6461.75/bin/cmake/win/bin/ctest.exe",
			"root" : "C:/Users/Silence/AppData/Local/JetBrains/Toolbox/apps/CLion/ch-0/213.6461.75/bin/cmake/win/share/cmake-3.21"
		},
		"version" : 
		{
			"isDirty" : false,
			"major" : 3,
			"minor" : 21,
			"patch" : 1,
			"string" : "3.21.1",
			"suffix" : ""
		}
	},
	"objects" : 
	[
		{
			"jsonFile" : "codemodel-v2-907408392394ead6c3d6.json",
			"kind" : "codemodel",
			"version" : 
			{
				"major" : 2,
				"minor" : 3
			}
		},
		{
			"jsonFile" : "cache-v2-64e27b7c9e9bf268db98.json",
			"kind" : "cache",
			"version" : 
			{
				"major" : 2,
				"minor" : 0
			}
		},
		{
			"jsonFile" : "cmakeFiles-v1-fc828d5035a281683c14.json",
			"kind" : "cmakeFiles",
			"version" : 
			{
				"major" : 1,
				"minor" : 0
			}
		},
		{
			"jsonFile" : "toolchains-v1-9787e8d9929df2d0675a.json",
			"kind" : "toolchains",
			"version" : 
			{
				"major" : 1,
				"minor" : 0
			}
		}
	],
	"reply" : 
	{
		"cache-v2" : 
		{
			"jsonFile" : "cache-v2-64e27b7c9e9bf268db98.json",
			"kind" : "cache",
			"version" : 
			{
				"major" : 2,
				"minor" : 0
			}
		},
		"cmakeFiles-v1" : 
		{
			"jsonFile" : "cmakeFiles-v1-fc828d5035a281683c14.json",
			"kind" : "cmakeFiles",
			"version" : 
			{
				"major" : 1,
				"minor" : 0
			}
		},
		"codemodel-v2" : 
		{
			"jsonFile" : "codemodel-v2-907408392394ead6c3d6.json",
			"kind" : "codemodel",
			"version" : 
			{
				"major" : 2,
				"minor" : 3
			}
		},
		"toolchains-v1" : 
		{
			"jsonFile" : "toolchains-v1-9787e8d9929df2d0675a.json",
			"kind" : "toolchains",
			"version" : 
			{
				"major" : 1,
				"minor" : 0
			}
		}
	}
}
